{"name":"O que fazemos","path":"/o-que-fazemos","sections":[{"__resolveType":"Header"},{"__resolveType":"site/sections/BannerPages.tsx"},{"__resolveType":"site/sections/RichText.tsx","text":"<p>New</p>"},{"__resolveType":"site/sections/Map.tsx","textMap":"<p>O Instituto Escola Conectada começou as suas atividades em novembro de 2020. Em fevereiro do ano seguinte foi realizada a instalação de internet de alta velocidade na primeira escola do programa: Escola Municipal Prudente de Moraes, em Miracema (RJ).</p>","titleMap":"Nossos números","linkIframeMap":"<iframe src='https://www.google.com/maps/d/u/0/embed?mid=1lFW2lx4RYWygzowEV0GimuJ1hN_JpcU&ehbc=2E312F&noprof=1' width='640' height='480'></iframe>"},{"__resolveType":"Footer"}],"__resolveType":"website/pages/Page.tsx"}